topsis/__init__.py
topsis/__main__.py
TOPSIS_Anubhav_101803051-1.0.1.dist-info/LICENCE
TOPSIS_Anubhav_101803051-1.0.1.dist-info/METADATA
TOPSIS_Anubhav_101803051-1.0.1.dist-info/WHEEL
TOPSIS_Anubhav_101803051-1.0.1.dist-info/entry_points.txt
TOPSIS_Anubhav_101803051-1.0.1.dist-info/top_level.txt
TOPSIS_Anubhav_101803051-1.0.1.dist-info/RECORD
