Metadata-Version: 2.1
Name: TOPSIS-Anubhav-101803051
Version: 1.0.1
Summary: Compute Topsis Scores/Ranks of a given csv file
Home-page: https://github.com/sharma-anubhav/Topsis
Author: Anubhav Sharma
Author-email: anubhav0399@gmail.com
License: MIT
Platform: UNKNOWN
Classifier: License :: OSI Approved :: MIT License
Classifier: Programming Language :: Python :: 3.6
Classifier: Programming Language :: Python :: 3.7
Classifier: Programming Language :: Python :: 3.8
Requires-Dist: topsis
